Metadata-Version: 2.1
Name: fmyar-binom-quantile
Version: 0.1.0
Summary: A example Python package
Home-page: https://example.com/
Author: Yaroslav Ilin
Author-email: fmyar@vk.com
License: BSD 2-clause
Platform: UNKNOWN
